profile_reddit_restapi_imp_local/ProfileRedditConstants.py
profile_reddit_restapi_imp_local/__init__.py
profile_reddit_restapi_imp_local/handler.py
profile_reddit_restapi_imp_local/search_reddit.py
profile_reddit_restapi_imp_local-0.0.38.dist-info/METADATA
profile_reddit_restapi_imp_local-0.0.38.dist-info/WHEEL
profile_reddit_restapi_imp_local-0.0.38.dist-info/top_level.txt
profile_reddit_restapi_imp_local-0.0.38.dist-info/RECORD
