Metadata-Version: 2.1
Name: profile-reddit-restapi-imp-local
Version: 0.0.38
Home-page: https://github.com/circles-zone/profile-reddit-restapi-imp-local-python-package
Author: Circles
Author-email: info@circlez.ai
Classifier: Programming Language :: Python :: 3
Classifier: License :: Other/Proprietary License
Classifier: Operating System :: OS Independent
Requires-Dist: praw >=7.4.0
Requires-Dist: tqdm >=4.64.1
Requires-Dist: requests
Requires-Dist: data-source-local
Requires-Dist: entity-type-local >=0.0.13
Requires-Dist: importer-local >=0.0.43
Requires-Dist: location-local
Requires-Dist: logger-local >=0.0.93
Requires-Dist: profile-local >=0.0.61
Requires-Dist: group-remote >=0.0.105
Requires-Dist: python-sdk-remote >=0.0.65
Requires-Dist: user-context-remote >=0.0.54
